ansys/scade/git/__init__.py
ansys/scade/git/git-310.srg
ansys/scade/git/git-37.srg
ansys/scade/git/git.srg
ansys/scade/git/register.py
ansys/scade/git/unregister.py
ansys/scade/git/almgtmerge/__main__.py
ansys/scade/git/almgtmerge/almgtmerge3.py
ansys/scade/git/etpmerge/__main__.py
ansys/scade/git/etpmerge/cache.py
ansys/scade/git/etpmerge/checkids.py
ansys/scade/git/etpmerge/etpmerge3.py
ansys/scade/git/etpmerge/fi.py
ansys/scade/git/etpmerge/utils.py
ansys/scade/git/etpmerge/visitor.py
ansys/scade/git/extension/gitclient.py
ansys/scade/git/extension/gitextcore.py
ansys/scade/git/extension/gitextension.py
ansys/scade/git/extension/ide.py
ansys/scade/git/extension/img/added.ico
ansys/scade/git/extension/img/clean.ico
ansys/scade/git/extension/img/commit.bmp
ansys/scade/git/extension/img/diff.bmp
ansys/scade/git/extension/img/error.ico
ansys/scade/git/extension/img/extern.ico
ansys/scade/git/extension/img/git.ico
ansys/scade/git/extension/img/modified.ico
ansys/scade/git/extension/img/refresh.bmp
ansys/scade/git/extension/img/removed.ico
ansys/scade/git/extension/img/stage.bmp
ansys/scade/git/extension/img/unstage.bmp
ansys/scade/git/extension/img/untracked.ico
ansys_scade_git-0.2.0.dist-info/entry_points.txt
ansys_scade_git-0.2.0.dist-info/LICENSE
ansys_scade_git-0.2.0.dist-info/WHEEL
ansys_scade_git-0.2.0.dist-info/METADATA
ansys_scade_git-0.2.0.dist-info/RECORD
