Metadata-Version: 2.3
Name: ansys-scade-git
Version: 0.2.0
Summary: SCADE GUI extensions and command line utilities for Git.
Keywords: Scade,Git,CM,Merge
Author-email: "Ansys, Inc." <pyansys.core@ansys.com>
Maintainer-email: "Ansys, Inc." <pyansys.core@ansys.com>
Requires-Python: >=3.7,!=3.8.*,!=3.9.*,<3.11
Classifier: Development Status :: 4 - Beta
Classifier: Programming Language :: Python :: 3
Classifier: License :: OSI Approved :: MIT License
Classifier: Operating System :: Microsoft :: Windows
Requires-Dist: ansys-scade-apitools
Requires-Dist: dulwich>=0.21.3
Requires-Dist: importlib-metadata >= 1.0; python_version < '3.8'
Requires-Dist: importlib-metadata >= 4.0; python_version >= '3.8'
Requires-Dist: lxml
Requires-Dist: build==1.2.2.post1 ; extra == "build"
Requires-Dist: twine==6.1.0 ; extra == "build"
Requires-Dist: ansys-sphinx-theme==1.3.2 ; extra == "doc"
Requires-Dist: jupyter_sphinx==0.5.3 ; extra == "doc"
Requires-Dist: nbsphinx==0.9.6 ; extra == "doc"
Requires-Dist: numpydoc==1.8.0 ; extra == "doc"
Requires-Dist: sphinx==8.1.3 ; extra == "doc"
Requires-Dist: sphinx-autodoc-typehints==3.0.1 ; extra == "doc"
Requires-Dist: sphinx-copybutton==0.5.2 ; extra == "doc"
Requires-Dist: sphinx_design==0.6.1 ; extra == "doc"
Requires-Dist: pytest==8.3.4 ; extra == "tests"
Requires-Dist: pytest-cov==6.0.0 ; extra == "tests"
Project-URL: Discussions, https://github.com/ansys/scade-git/discussions
Project-URL: Documentation, https://git.scade.docs.pyansys.com
Project-URL: Homepage, https://www.ansys.com/products/embedded-software/ansys-scade-suite
Project-URL: Issues, https://github.com/ansys/scade-git/issues
Project-URL: Releases, https://github.com/ansys/scade-git/releases
Project-URL: Source, https://github.com/ansys/scade-git
Provides-Extra: build
Provides-Extra: doc
Provides-Extra: tests
